hyperlog.py
hyperlog-0.2.0.dist-info/licenses/LICENSE
hyperlog-0.2.0.dist-info/METADATA
hyperlog-0.2.0.dist-info/WHEEL
hyperlog-0.2.0.dist-info/top_level.txt
hyperlog-0.2.0.dist-info/RECORD
