Metadata-Version: 2.4
Name: hyperlog
Version: 0.2.0
Summary: One import. Better logging. Simple. Batteries included.
Author: Yusuf Khan
License: MIT
Project-URL: Homepage, https://github.com/yusuf-jkhan1//hyperlog
Project-URL: Repository, https://github.com/yusuf-jkhan1//hyperlog
Project-URL: Issues, https://github.com/yusuf-jkhan1//hyperlog/issues
Keywords: logging,decorator,performance,monitoring,timer,beautiful
Classifier: Development Status :: 4 - Beta
Classifier: Intended Audience :: Developers
Classifier: License :: OSI Approved :: MIT License
Classifier: Operating System :: OS Independent
Classifier: Programming Language :: Python :: 3
Classifier: Programming Language :: Python :: 3.7
Classifier: Programming Language :: Python :: 3.8
Classifier: Programming Language :: Python :: 3.9
Classifier: Programming Language :: Python :: 3.10
Classifier: Programming Language :: Python :: 3.11
Classifier: Programming Language :: Python :: 3.12
Classifier: Topic :: Software Development :: Libraries :: Python Modules
Classifier: Topic :: System :: Logging
Requires-Python: >=3.7
License-File: LICENSE
Requires-Dist: loguru>=0.6.0
Provides-Extra: dev
Requires-Dist: loguru>=0.6.0; extra == "dev"
Requires-Dist: pytest>=7.0; extra == "dev"
Requires-Dist: pytest-asyncio>=0.20; extra == "dev"
Requires-Dist: pytest-cov>=4.0; extra == "dev"
Requires-Dist: black>=22.0; extra == "dev"
Requires-Dist: ruff>=0.1; extra == "dev"
Requires-Dist: mypy>=1.0; extra == "dev"
Dynamic: license-file
